.coveragerc
MANIFEST.in
README.md
setup.cfg
setup.py
chilero/__init__.py
chilero.egg-info/PKG-INFO
chilero.egg-info/SOURCES.txt
chilero.egg-info/dependency_links.txt
chilero.egg-info/namespace_packages.txt
chilero.egg-info/requires.txt
chilero.egg-info/top_level.txt
chilero/web/__init__.py
chilero/web/application.py
chilero/web/resource.py
chilero/web/response.py
chilero/web/test.py
chilero/web/view.py
tests/__init__.py
tests/test_encoder.py
tests/test_resource.py
tests/test_web.py