Metadata-Version: 1.1
Name: chilero
Version: 0.5.1
Summary: A micro framework... A la Tortrix!
Home-page: https://github.com/dmonroy/chilero
Author: Darwin Monroy
Author-email: contact@darwinmonroy.com
License: UNKNOWN
Platform: UNKNOWN
Classifier: Development Status :: 4 - Beta
Classifier: Environment :: Web Environment
Classifier: Intended Audience :: Developers
Classifier: License :: OSI Approved :: MIT License
Classifier: Programming Language :: Python :: 3.4
Classifier: Programming Language :: Python :: 3.5
Classifier: Programming Language :: Python :: 3.6
Classifier: Topic :: Internet :: WWW/HTTP
Classifier: Topic :: Software Development :: Libraries :: Application Frameworks
